PyQt5/Qt5/qsci/api/python/PyQtChart.api
PyQt5/QtChart.pyd
PyQt5/QtChart.pyi
PyQt5/bindings/QtChart/QtChart.toml
PyQt5/bindings/QtChart/QtChartmod.sip
PyQt5/bindings/QtChart/qabstractaxis.sip
PyQt5/bindings/QtChart/qabstractbarseries.sip
PyQt5/bindings/QtChart/qabstractseries.sip
PyQt5/bindings/QtChart/qarealegendmarker.sip
PyQt5/bindings/QtChart/qareaseries.sip
PyQt5/bindings/QtChart/qbarcategoriesaxis.sip
PyQt5/bindings/QtChart/qbarcategoryaxis.sip
PyQt5/bindings/QtChart/qbarlegendmarker.sip
PyQt5/bindings/QtChart/qbarseries.sip
PyQt5/bindings/QtChart/qbarset.sip
PyQt5/bindings/QtChart/qboxplotlegendmarker.sip
PyQt5/bindings/QtChart/qboxplotseries.sip
PyQt5/bindings/QtChart/qboxset.sip
PyQt5/bindings/QtChart/qcandlesticklegendmarker.sip
PyQt5/bindings/QtChart/qcandlestickmodelmapper.sip
PyQt5/bindings/QtChart/qcandlestickseries.sip
PyQt5/bindings/QtChart/qcandlestickset.sip
PyQt5/bindings/QtChart/qcategoryaxis.sip
PyQt5/bindings/QtChart/qchart.sip
PyQt5/bindings/QtChart/qchartglobal.sip
PyQt5/bindings/QtChart/qchartview.sip
PyQt5/bindings/QtChart/qdatetimeaxis.sip
PyQt5/bindings/QtChart/qhbarmodelmapper.sip
PyQt5/bindings/QtChart/qhboxplotmodelmapper.sip
PyQt5/bindings/QtChart/qhcandlestickmodelmapper.sip
PyQt5/bindings/QtChart/qhorizontalbarseries.sip
PyQt5/bindings/QtChart/qhorizontalpercentbarseries.sip
PyQt5/bindings/QtChart/qhorizontalstackedbarseries.sip
PyQt5/bindings/QtChart/qhpiemodelmapper.sip
PyQt5/bindings/QtChart/qhxymodelmapper.sip
PyQt5/bindings/QtChart/qlegend.sip
PyQt5/bindings/QtChart/qlegendmarker.sip
PyQt5/bindings/QtChart/qlineseries.sip
PyQt5/bindings/QtChart/qlogvalueaxis.sip
PyQt5/bindings/QtChart/qpercentbarseries.sip
PyQt5/bindings/QtChart/qpielegendmarker.sip
PyQt5/bindings/QtChart/qpieseries.sip
PyQt5/bindings/QtChart/qpieslice.sip
PyQt5/bindings/QtChart/qpolarchart.sip
PyQt5/bindings/QtChart/qscatterseries.sip
PyQt5/bindings/QtChart/qsplineseries.sip
PyQtChart-5.15.7.dist-info/WHEEL
PyQtChart-5.15.7.dist-info/METADATA
PyQtChart-5.15.7.dist-info/RECORD
