Metadata-Version: 2.1
Name: PyQtChart
Version: 5.15.7
Requires-Python: >=3.8
Summary: Python bindings for the Qt Charts library
Project-Url: homepage, https://www.riverbankcomputing.com/software/pyqtchart/
Requires-Dist: PyQt5 (>=5.15.4)
License: GPL v3
Author-Email: Riverbank Computing Limited <info@riverbankcomputing.com>
